sqldeps/__init__.py
sqldeps/extractor.py
sqldeps/models.py
sql_dependency_parser-0.0.12.dist-info/METADATA
sql_dependency_parser-0.0.12.dist-info/WHEEL
sql_dependency_parser-0.0.12.dist-info/top_level.txt
sql_dependency_parser-0.0.12.dist-info/RECORD
