Metadata-Version: 2.1
Name: sql-dependency-parser
Version: 0.0.12
Summary: A tool to extract dependencies from SQL queries.
Author-email: Cainã Silva <coutodasilva@wisc.edu>, Matt Christie <mjchristie@wisc.edu>
Classifier: Programming Language :: Python :: 3
Classifier: Programming Language :: Python :: 3.12
Classifier: Operating System :: OS Independent
Requires-Python: >=3.12
Requires-Dist: ipykernel>=6.29.5
Requires-Dist: sqlalchemy>=2.0.36
Requires-Dist: sqlglot>=26.0.0
